[{"rank": 1, "player": "Taiga", "country": "Japan", "time": "1:46:324", "std": "NB", "video": "https://youtu.be/fCB5NVO63zw", "isCr?": true}, {"rank": 2, "player": "Towa", "country": "Japan", "time": "1:47:090", "std": "NB", "video": "https://youtu.be/bW5ebKspHU8", "isCr?": false}, {"rank": 3, "player": "J", "country": "Japan", "time": "1:47:899", "std": "NB", "video": "https://www.youtube.com/watch?v=tQRT7-8sJk4", "isCr?": false}, {"rank": 4, "player": "TB1", "country": "Switzerland", "time": "1:47:937", "std": "NB", "video": "https://www.youtube.com/watch?v=JjiOOn_YcuM", "isCr?": true}, {"rank": 5, "player": "Beta", "country": "Japan", "time": "1:47:988", "std": "NB", "video": "https://www.youtube.com/watch?v=ORf7Ps8ceEA", "isCr?": false}, {"rank": 6, "player": "MiTi", "country": "Japan", "time": "1:48:085", "std": "NB", "video": "https://www.youtube.com/watch?v=tNHyza2TzUQ", "isCr?": false}, {"rank": 7, "player": "ZEG", "country": "Japan", "time": "1:48:348", "std": "NB", "video": "https://www.youtube.com/watch?v=z6LdQBP4AsI", "isCr?": false}, {"rank": 8, "player": "Rupa", "country": "Japan", "time": "1:48:387", "std": "NB", "video": null, "isCr?": false}, {"rank": 9, "player": "FULLMETAL", "country": "Japan", "time": "1:48:533", "std": "NB", "video": null, "isCr?": false}, {"rank": 10, "player": "Gupe", "country": "Japan", "time": "1:48:639", "std": "NB", "video": "https://www.youtube.com/watch?v=gjnn56zv0P8", "isCr?": false}, {"rank": 11, "player": "Spark", "country": "Japan", "time": "1:48:717", "std": "NB", "video": "http://www.youtube.com/watch?v=GnUgw7EheS0", "isCr?": false}, {"rank": 12, "player": "Quantum", "country": "USA", "time": "1:48:732", "std": "NB", "video": "https://cdn.discordapp.com/attachments/123861145449660417/997019465063616594/20220713_225859.jpg", "isCr?": true}, {"rank": 13, "player": "k@\u304c\u3061", "country": "Japan", "time": "1:48:747", "std": "NB", "video": "https://www.youtube.com/watch?v=Ieq2kdu3nn8", "isCr?": false}, {"rank": 14, "player": "9", "country": "Japan", "time": "1:48:767", "std": "NB", "video": "https://youtu.be/wYeg0l9oHks", "isCr?": false}, {"rank": 15, "player": "Amemiya", "country": "Japan", "time": "1:48:778", "std": "NB", "video": null, "isCr?": false}, {"rank": 16, "player": "Folk", "country": "Japan", "time": "1:48:975", "std": "NB", "video": "https://www.youtube.com/watch?v=zen3OHTPmgE", "isCr?": false}, {"rank": 17, "player": "Abel P", "country": "Spain", "time": "1:49:033", "std": "NB", "video": "https://www.youtube.com/watch?v=TGRoAGUzux4", "isCr?": true}, {"rank": 18, "player": "DarkMatter", "country": "Japan", "time": "1:49:077", "std": "NB", "video": "https://www.youtube.com/watch?v=ZXh4Yz3wKEs", "isCr?": false}, {"rank": 19, "player": "Ameyuki", "country": "Japan", "time": "1:49:124", "std": "NB", "video": "https://youtu.be/Z_vr_REZbBc", "isCr?": false}, {"rank": 20, "player": "Abel M", "country": "UK", "time": "1:49:496", "std": "NB", "video": "https://www.youtube.com/watch?v=aL5WYCS_Cjc", "isCr?": true}, {"rank": 21, "player": "\u3084\u307f", "country": "Japan", "time": "1:49:656", "std": "NB", "video": null, "isCr?": false}, {"rank": 22, "player": "yutakart", "country": "Japan", "time": "1:49:679", "std": "NB", "video": "https://www.youtube.com/watch?v=Gv13TXveIYE", "isCr?": false}, {"rank": 23, "player": "Unreal", "country": "UK", "time": "1:49:837", "std": "NB", "video": "https://www.youtube.com/watch?v=mAS8DuSc0Cg", "isCr?": false}, {"rank": 24, "player": "Bdash", "country": "Japan", "time": "1:50:040", "std": "NB", "video": "http://www.wrvids.com/Mario%20Kart/MKDS/Wifi/lm100cc-150040-BDash.flv", "isCr?": false}, {"rank": 24, "player": "\u5d50\u5c71", "country": "Japan", "time": "1:50:040", "std": "NB", "video": null, "isCr?": false}, {"rank": 26, "player": "Kanashimi", "country": "Japan", "time": "1:50:345", "std": "NB", "video": null, "isCr?": false}, {"rank": 27, "player": "\u30ab\u30a4\u30eb", "country": "USA", "time": "1:50:448", "std": "NB", "video": "https://www.youtube.com/watch?v=05C9vECw1t0", "isCr?": false}, {"rank": 28, "player": "Abyssion", "country": "UK", "time": "1:50:933", "std": "NB", "video": "https://www.youtube.com/watch?v=FAXuevHkZW8", "isCr?": false}, {"rank": 29, "player": "\u3086\u304d\u308a\u3093", "country": "Japan", "time": "1:51:311", "std": "NB", "video": null, "isCr?": false}, {"rank": 30, "player": "Amaris\u2606", "country": "Japan", "time": "1:51:541", "std": "NB", "video": null, "isCr?": false}, {"rank": 31, "player": "Nano", "country": "USA", "time": "1:51:654", "std": "NB", "video": null, "isCr?": false}, {"rank": 32, "player": "George", "country": "Japan", "time": "1:51:762", "std": "NB", "video": null, "isCr?": false}, {"rank": 33, "player": "\u307f\u3064\u3070\u3061\u30cf\u30c3\u30c1\u266a", "country": "Japan", "time": "1:51:780", "std": "NB", "video": "https://www.youtube.com/watch?v=ok1-Qa3eDVw", "isCr?": false}, {"rank": 34, "player": "arshe", "country": "Japan", "time": "1:51:817", "std": "NB", "video": null, "isCr?": false}, {"rank": 35, "player": "B99", "country": "France", "time": "1:52:118", "std": "NB", "video": "https://www.youtube.com/watch?v=EJo3N3E6msQ", "isCr?": true}, {"rank": 36, "player": "Swallow", "country": "Japan", "time": "1:52:778", "std": "NB", "video": "https://www.youtube.com/watch?v=k8zq5C2GyiQ", "isCr?": false}, {"rank": 37, "player": "Advance", "country": "Japan", "time": "1:53:045", "std": "NB", "video": null, "isCr?": false}, {"rank": 38, "player": "Pikalex", "country": "Italy", "time": "1:53:148", "std": "NB", "video": null, "isCr?": true}, {"rank": 39, "player": "\u306b\u3053\u3089", "country": "Japan", "time": "1:54:410", "std": "NB", "video": "http://www.nicovideo.jp/watch/sm2295910", "isCr?": false}, {"rank": 40, "player": "Death", "country": "USA", "time": "1:54:728", "std": "NB", "video": "https://www.youtube.com/watch?v=P6Lz7e02Dp4", "isCr?": false}, {"rank": 41, "player": "Kazumin", "country": "Japan", "time": "1:55:171", "std": "NB", "video": "https://youtu.be/gdlB5UslAUw", "isCr?": false}, {"rank": 42, "player": "Snaker", "country": "France", "time": "1:55:776", "std": "NB", "video": null, "isCr?": false}, {"rank": 43, "player": "\u3051\u3093\u3044\u3061", "country": "Japan", "time": "2:08:18", "std": "NB", "video": null, "isCr?": false}]